{
  "noise": 0,
  "static.other": 0,
  "Sky": 0,
  "Blurred area": 0,
  "Sidebars": 0,
  "Grid structure": 0,
  "UNDEFINED": 0,
  "vehicle.car": 1,
  "car": 1,
  "Car 1": 1,
  "Car 2": 1,
  "Car 3": 1,
  "Car 4": 1,
  "CAR": 1,
  "vehicle.truck": 2,
  "truck": 2,
  "Truck 1": 2,
  "Truck 2": 2,
  "Truck 3": 2,
  "TRUCK": 2,
  "vehicle.bicycle": 3,
  "bicycle": 3,
  "Bicycle 1": 3,
  "Bicycle 2": 3,
  "Bicycle 3": 3,
  "Bicycle 4": 3,
  "BICYCLE": 3,
  "BICYCLIST": 3,
  "vehicle.bus.bendy": 4,
  "vehicle.bus.rigid": 4,
  "bus": 4,
  "vehicle.motorcycle": 5,
  "motorcycle": 5,
  "MOTORCYCLIST": 5,
  "MOTORCYCLE": 5,
  "vehicle.emergency.ambulance": 6,
  "vehicle.emergency.police": 6,
  "emergency_vehicles": 6,
  "vehicle.construction": 7,
  "vehicle.trailer": 7,
  "other_vehicle": 7,
  "Small vehicles 1": 7,
  "Small vehicles 2": 7,
  "Small vehicles 3": 7,
  "Utility vehicle 1": 7,
  "Utility vehicle 2": 7,
  "Tractor": 7,
  "OTHER_VEHICLE": 7,
  "vehicle.ego": 8,
  "Ego car": 8,
  "pedestrian": 9,
  "human.pedestrian.child`": 9,
  "Pedestrian 1": 9,
  "human.pedestrian.police_officer": 9,
  "human.pedestrian.stroller": 9,
  "human.pedestrian.construction_worker": 9,
  "Pedestrian 2": 9,
  "human.pedestrian.wheelchair": 9,
  "human.pedestrian.adult": 9,
  "PEDESTRIAN": 9,
  "human.pedestrian.personal_mobility": 9,
  "Pedestrian 3": 9,
  "animal": 10,
  "Animals": 10,
  "VEGETATION": 11,
  "Nature object": 11,
  "static.vegetation": 11,
  "TREE_TRUNK": 11,
  "flat.driveable_surface": 12,
  "Zebra crossing": 12,
  "Slow drive area": 12,
  "Dashed line": 12,
  "RD normal street": 12,
  "Parking area": 12,
  "Speed bumper": 12,
  "Painted driv. instr.": 12,
  "Rain dirt": 12,
  "Drivable cobblestone": 12,
  "ROAD": 12,
  "LANE_MARKER": 12,
  "flat.other": 13,
  "flat.sidewalk": 13,
  "flat.terrain": 13,
  "Non-drivable street": 13,
  "RD restricted area": 13,
  "Sidewalk": 13,
  "Solid line": 13,
  "WALKABLE": 13,
  "OTHER_GROUND": 13,
  "SIDEWALK": 13,
  "movable_object.trafficcone": 14,
  "movable_object.barrier": 14,
  "Curbstone": 14,
  "CURB": 14,
  "Road blocks": 14,
  "movable_object.debris": 14,
  "movable_object.pushable_pullable": 14,
  "Obstacles / trash": 14,
  "CONSTRUCTION_CONE": 14,
  "SIGN": 15,
  "Traffic signal 3": 15,
  "Poles": 15,
  "TRAFFIC_LIGHT": 15,
  "Traffic signal 2": 15,
  "Traffic guide obj.": 15,
  "Traffic sign 1": 15,
  "Traffic signal 1": 15,
  "Traffic sign 3": 15,
  "BUILDING": 15,
  "static.manmade": 15,
  "static_object.bicycle_rack": 15,
  "Electronic traffic": 15,
  "Irrelevant signs": 15,
  "Signal corpus": 15,
  "Buildings": 15,
  "POLE": 15,
  "Traffic sign 2": 15
}